forgram/__init__.py
forgram/bot.py
forgram/exceptions.py
forgram/models.py
forgram/storage.py
forgram-2.2.0.dist-info/licenses/LICENSE
forgram-2.2.0.dist-info/METADATA
forgram-2.2.0.dist-info/WHEEL
forgram-2.2.0.dist-info/top_level.txt
forgram-2.2.0.dist-info/RECORD
