Metadata-Version: 2.4
Name: forgram
Version: 2.2.0
Summary: Самая полная библиотека для Telegram ботов с 150+ методами
Author: Forgram Team
License: MIT License
Project-URL: Homepage, https://github.com/yourusername/forgram
Project-URL: Documentation, https://github.com/yourusername/forgram/blob/main/README.md
Project-URL: Repository, https://github.com/yourusername/forgram.git
Project-URL: Bug Tracker, https://github.com/yourusername/forgram/issues
Classifier: Development Status :: 5 - Production/Stable
Classifier: Intended Audience :: Developers
Classifier: License :: OSI Approved :: MIT License
Classifier: Programming Language :: Python :: 3
Classifier: Programming Language :: Python :: 3.7
Classifier: Programming Language :: Python :: 3.8
Classifier: Programming Language :: Python :: 3.9
Classifier: Programming Language :: Python :: 3.10
Classifier: Programming Language :: Python :: 3.11
Classifier: Topic :: Software Development :: Libraries :: Python Modules
Classifier: Topic :: Communications :: Chat
Requires-Python: >=3.7
License-File: LICENSE
Requires-Dist: aiohttp>=3.8.0
Dynamic: license-file
